video-images-creator/__init__.py
video-images-creator/build_screen.py
video-images-creator/moveL2R.py
video-images-creator/moveR2L.py
video-images-creator/video_creator.py
video_images_creator/__init__.py
video_images_creator/video_creator.py
video_images_creator-0.1.0.dist-info/LICENSE
video_images_creator-0.1.0.dist-info/METADATA
video_images_creator-0.1.0.dist-info/WHEEL
video_images_creator-0.1.0.dist-info/top_level.txt
video_images_creator-0.1.0.dist-info/RECORD
