Metadata-Version: 2.1
Name: video-images-creator
Version: 0.1.0
Summary: A example Python package
Home-page: 
Author: Nikhil Sharma
Author-email: nikhilsharma972@gmail.com
License: BSD 2-clause
Classifier: Development Status :: 1 - Planning
License-File: LICENSE
Requires-Dist: opencv-python
Requires-Dist: numpy
Requires-Dist: pillow
